centerit/__init__.py
centerit-0.6.dist-info/LICENSE
centerit-0.6.dist-info/METADATA
centerit-0.6.dist-info/WHEEL
centerit-0.6.dist-info/top_level.txt
centerit-0.6.dist-info/RECORD
