Metadata-Version: 2.1
Name: centerit
Version: 0.6
Summary: A library for centering python gui windows.
Home-page: https://github.com/MrinmoyHaloi/centerit
Author: Mrinmoy Haloi
Author-email: <mhedeetz.business@gmail.com>
License: UNKNOWN
Keywords: python,gui
Platform: UNKNOWN
Classifier: Development Status :: 1 - Planning
Classifier: Intended Audience :: Developers
Classifier: Programming Language :: Python :: 3
Classifier: License :: OSI Approved :: GNU General Public License v2 (GPLv2)
Classifier: Natural Language :: English
Classifier: Operating System :: Unix
Classifier: Operating System :: Microsoft :: Windows
